{
  "project_info": {
    "project_number": "464842637746",
    "project_id": "myplanetapp-4337b",
    "storage_bucket": "myplanetapp-4337b.appspot.com"
  },
  "client": [
    {
      "client_info": {
        "mobilesdk_app_id": "1:464842637746:android:7e1a5d5f98b7887287e4ab",
        "android_client_info": {
          "package_name": "kz.jumysbar.intelteam"
        }
      },
      "oauth_client": [
        {
          "client_id": "464842637746-faovgpvbtd545jhdh98likc6amuoh6vj.apps.googleusercontent.com",
          "client_type": 3
        }
      ],
      "api_key": [
        {
          "current_key": "AIzaSyArodoqi42jiKu_IibVdRRfRrEFjqzN4uQ"
        }
      ],
      "services": {
        "appinvite_service": {
          "other_platform_oauth_client": [
            {
              "client_id": "464842637746-faovgpvbtd545jhdh98likc6amuoh6vj.apps.googleusercontent.com",
              "client_type": 3
            }
          ]
        }
      }
    }
  ],
  "configuration_version": "1"
}